backupy/__init__.py
backupy/__main__.py
backupy/backupman.py
backupy/cli.py
backupy/config.py
backupy/fileman.py
backupy/filescanner.py
backupy/gui.py
backupy/logman.py
backupy/statusbar.py
backupy/transferlists.py
backupy/treedisplay.py
backupy/utils.py
BackuPy-1.10.1.dist-info/LICENSE
BackuPy-1.10.1.dist-info/METADATA
BackuPy-1.10.1.dist-info/WHEEL
BackuPy-1.10.1.dist-info/entry_points.txt
BackuPy-1.10.1.dist-info/top_level.txt
BackuPy-1.10.1.dist-info/RECORD
