Metadata-Version: 2.1
Name: BackuPy
Version: 1.10.1
Summary: A simple backup program in python with an emphasis on data integrity and transparent behaviour
Home-page: https://github.com/elesiuta/backupy
License: GPLv3
Platform: UNKNOWN
Classifier: Programming Language :: Python :: 3
Classifier: License :: OSI Approved :: GNU General Public License v3 (GPLv3)
Classifier: Operating System :: OS Independent
Classifier: Topic :: System :: Archiving :: Backup
Classifier: Topic :: System :: Archiving :: Mirroring
Classifier: Topic :: Utilities
Classifier: Intended Audience :: End Users/Desktop
Classifier: Environment :: Console
Classifier: Development Status :: 5 - Production/Stable
License-File: LICENSE
